hugedict-2.14.6.dist-info/METADATA
hugedict-2.14.6.dist-info/WHEEL
hugedict-2.14.6.dist-info/licenses/LICENSE
hugedict/__init__.py
hugedict/cachedict.py
hugedict/chained_mapping.py
hugedict/core.cpython-310-aarch64-linux-gnu.so
hugedict/core/__init__.pyi
hugedict/core/rocksdb.pyi
hugedict/misc.py
hugedict/parallel.py
hugedict/prelude.py
hugedict/py.typed
hugedict/rocksdb.py
hugedict/sqlite.py
hugedict/sqlitedict.py
hugedict/types.py
hugedict-2.14.6.dist-info/RECORD
