Metadata-Version: 2.4
Name: hugedict
Version: 2.14.6
Classifier: Programming Language :: Rust
Classifier: Programming Language :: Python :: Implementation :: CPython
Requires-Dist: orjson>=3.9.0,<4.0.0
Requires-Dist: loguru>=0.7.0,<0.8.0
Requires-Dist: zstandard>=0.23.0,<1.0.0
Requires-Dist: tqdm>=4.64.0,<5.0.0
Requires-Dist: timer4>=1.1.0,<2.0.0
Requires-Dist: pytest>=7.1.3,<8.0.0 ; extra == 'dev'
Requires-Dist: pytest-cov>=4.0.0,<5.0.0 ; extra == 'dev'
Requires-Dist: black>=22.10.0,<23.0.0 ; extra == 'dev'
Provides-Extra: dev
License-File: LICENSE
Summary: A dictionary-like object that is friendly with multiprocessing and uses key-value databases (e.g., RocksDB) as the underlying storage.
Author-email: Binh Vu <binh@toan2.com>
Requires-Python: >=3.8
Project-URL: Homepage, https://github.com/binh-vu/hugedict
Project-URL: Repository, https://github.com/binh-vu/hugedict
